LICENSE.GPL
LICENSE.txt
README.txt
setup.py
Products/__init__.py
Products.CustomOverrides.egg-info/PKG-INFO
Products.CustomOverrides.egg-info/SOURCES.txt
Products.CustomOverrides.egg-info/dependency_links.txt
Products.CustomOverrides.egg-info/entry_points.txt
Products.CustomOverrides.egg-info/not-zip-safe
Products.CustomOverrides.egg-info/requires.txt
Products.CustomOverrides.egg-info/top_level.txt
Products/CustomOverrides/__init__.py
Products/CustomOverrides/configure.zcml
Products/CustomOverrides/profiles.zcml
Products/CustomOverrides/browser/__init__.py
Products/CustomOverrides/browser/configure.zcml
Products/CustomOverrides/browser/interfaces.py
Products/CustomOverrides/browser/javascript.pt
Products/CustomOverrides/browser/style.pt
Products/CustomOverrides/profiles/default/viewlets.xml
docs/HISTORY.txt