Metadata-Version: 1.0
Name: Products.CustomOverrides
Version: 1.0.3
Summary: Custom CSS and JS injection for Plone
Home-page: http://plone.org/products/customoverrides/
Author: Goldmund, Wyldebeast & Wunderliebe
Author-email: info@gw20e.com
License: UNKNOWN
Keywords: Plone custom CSS JS
Platform: UNKNOWN
Classifier: Programming Language :: Python
Classifier: Topic :: Software Development :: Libraries :: Python Modules
